{
  "heading": "Our Services",
  "intro": "Bookkeeping and financial support services for businesses and organizations that value accurate, consistent records.",
  "categories": [
    {
      "name": "Financial Reporting & Support",
      "icon": "📊",
      "summary": "Practical financial reporting and support to keep your records accurate, organized, and aligned.",
      "items": [
        {
          "name": "Financial Statement Preparation",
          "description": "Preparation of clear, accurate financial statements including income statements, balance sheets, and cash flow reports."
        },
        {
          "name": "Account Reconciliation",
          "description": "Ensuring your bank and credit accounts are accurate, complete, and aligned with your records."
        },
        {
          "name": "Financial Analysis",
          "description": "Straightforward review of your financial data to support informed, practical business decisions."
        },
        {
          "name": "Year-End Reporting",
          "description": "Organized year-end financial reporting to support tax preparation and compliance."
        }
      ],
      "summary2": "Summary2"
    },
    {
      "name": "Bookkeeping",
      "icon": "📒",
      "summary": "Reliable bookkeeping services to keep your records accurate, up to date, and consistent throughout the year. <br><br>Best suited for businesses that are maintaining or ready to maintain accurate financial records.",
      "items": [
        {
          "name": "Transaction Recording",
          "description": "Ongoing recording and organization of income and expense transactions."
        },
        {
          "name": "Payroll Processing",
          "description": "Accurate payroll processing, including deductions and required remittances."
        },
        {
          "name": "Accounts Payable & Receivable",
          "description": "Management of invoicing and bill payments to support steady cash flow."
        },
        {
          "name": "GST / HST Filing",
          "description": "Preparation and filing of GST/HST returns to keep you compliant and on schedule."
        }
      ],
      "summary2": "SUMMARY2"

    },
    {
      "name": "CLEANUP & CATCH-UP",
      "icon": "📂",
      "summary": "For businesses that need their financial records brought up to date and properly organized.<br><br>Accepted on a limited basis depending on current capacity.",
      "items": [
        {
          "name": "Historical Bookkeeping",
          "description": "Bringing past financial records up to date with accurate and organized transaction recording."
        },
        {
          "name": "Account Cleanup & Correction",
          "description": "Reviewing and correcting inconsistencies to ensure your records are complete and reliable."
        },
        {
          "name": "Reconciliation Catch-Up",
          "description": "Completing overdue bank and credit reconciliations to align your accounts"
        },
        {
          "name": "Transition to Ongoing Bookkeeping",
          "description": "Preparing your records for a smooth transition into consistent, ongoing bookkeeping."
        }
      ],
      "summary2": "SUMMARY2"
    }
  ],
  "ctaHeading": "Ready to Get Started?",
  "ctaText": "Contact us today to discuss your accounting needs. We'd love to work with you.",
  "ctaButtonText": "Contact Us"
}
